setup.py
tempodb_pandas/__init__.py
tempodb_pandas.egg-info/PKG-INFO
tempodb_pandas.egg-info/SOURCES.txt
tempodb_pandas.egg-info/dependency_links.txt
tempodb_pandas.egg-info/requires.txt
tempodb_pandas.egg-info/top_level.txt