Metadata-Version: 1.1
Name: tempodb-pandas
Version: 0.1.1
Summary: Pandas functions for converting between Tempo data types
Home-page: https://github.com/ixmatus/tempodb-pandas
Author: Parnell Springmeyer
Author-email: parnell@ixmat.us
License: UNKNOWN
Download-URL: https://github.com/ixmatus/tempodb-pandas
Platform: UNKNOWN
